c3cli/__init__.py
c3cli/billing.py
c3cli/cli.py
c3cli/comfyui.py
c3cli/instances.py
c3cli/jobs.py
c3cli/llm.py
c3cli/output.py
c3cli/renders.py
c3cli/user.py
c3cli/tui/__init__.py
c3cli/tui/job_monitor.py
c3_cli-0.4.0.dist-info/METADATA
c3_cli-0.4.0.dist-info/WHEEL
c3_cli-0.4.0.dist-info/entry_points.txt
c3_cli-0.4.0.dist-info/RECORD
