Metadata-Version: 2.4
Name: c3-cli
Version: 0.4.0
Summary: CLI for Compute3 - GPU orchestration and LLM API
Project-URL: Homepage, https://compute3.ai
Project-URL: Documentation, https://docs.compute3.ai
Author-email: Compute3 <support@compute3.ai>
License-Expression: MIT
Requires-Python: >=3.10
Requires-Dist: c3-sdk[comfyui]>=0.4.0
Requires-Dist: openai>=2.8.1
Requires-Dist: rich>=14.2.0
Requires-Dist: typer>=0.20.0
Requires-Dist: websocket-client>=1.6.0
Provides-Extra: dev
Requires-Dist: pytest>=8.0.0; extra == 'dev'
Requires-Dist: ruff>=0.3.0; extra == 'dev'
